{
  "Brock": "タケシ",
  "Misty": "カスミ",
  "Lt. Surge": "マチス",
  "Erika": "エリカ",
  "Koga": "キョウ",
  "Sabrina": "ナツメ",
  "Blaine": "カツラ",
  "Giovanni": "サカキ",

  "Lorelei": "カンナ",
  "Bruno": "シバ",
  "Agatha": "キクコ",
  "Lance": "ワタル",

  "Falkner": "ハヤト",
  "Bugsy": "ツクシ",
  "Whitney": "アカネ",
  "Morty": "マツバ",
  "Chuck": "シジマ",
  "Jasmine": "ミカン",
  "Pryce": "ヤナギ",
  "Clair": "イブキ",

  "Aaron": "リョウ",
  "Bertha": "キクノ",
  "Flint": "オーバ",
  "Lucian": "ゴヨウ",
  "Cynthia": "シロナ",

  "Roark": "ヒョウタ",
  "Gardenia": "ナタネ",
  "Maylene": "スモモ",
  "Wake": "マキシ",
  "Fantina": "メリッサ",
  "Byron": "トウガン",
  "Candice": "スズナ",
  "Volkner": "デンジ",

  "Ty": "ダイ",
  "Sue": "スー",
  "Mike": "マイク",
  "Nat": "ナット"
}
